epo_ops/__init__.py
epo_ops/__version__.py
epo_ops/api.py
epo_ops/exceptions.py
epo_ops/models.py
epo_ops/utils.py
epo_ops/middlewares/__init__.py
epo_ops/middlewares/middleware.py
epo_ops/middlewares/cache/__init__.py
epo_ops/middlewares/cache/dogpile/__init__.py
epo_ops/middlewares/cache/dogpile/dogpile.py
epo_ops/middlewares/cache/dogpile/helpers.py
epo_ops/middlewares/throttle/__init__.py
epo_ops/middlewares/throttle/throttler.py
epo_ops/middlewares/throttle/utils.py
epo_ops/middlewares/throttle/storages/__init__.py
epo_ops/middlewares/throttle/storages/sqlite.py
epo_ops/middlewares/throttle/storages/storage.py
python_epo_ops_client-4.2.1.dist-info/licenses/LICENSE
python_epo_ops_client-4.2.1.dist-info/METADATA
python_epo_ops_client-4.2.1.dist-info/WHEEL
python_epo_ops_client-4.2.1.dist-info/top_level.txt
python_epo_ops_client-4.2.1.dist-info/RECORD
