Metadata-Version: 2.4
Name: python-epo-ops-client
Version: 4.2.1
Summary: Python client for EPO OPS, the European Patent Office's Open Patent Services API.
Home-page: https://github.com/ip-tools/python-epo-ops-client
Download-URL: https://pypi.org/project/python-epo-ops-client/#files
Author: George Song
Author-email: george@monozuku.com
Maintainer: Andreas Motl
Maintainer-email: andreas.motl@ip-tools.org
Keywords: ops,epo,epo-ops,patent-data,patent-office,patent-data-api,european patent office,open patent services
Classifier: Development Status :: 5 - Production/Stable
Classifier: Intended Audience :: Developers
Classifier: Natural Language :: English
Classifier: License :: OSI Approved :: Apache Software License
Classifier: Programming Language :: Python
Classifier: Programming Language :: Python :: 3.6
Classifier: Programming Language :: Python :: 3.7
Classifier: Programming Language :: Python :: 3.8
Classifier: Programming Language :: Python :: 3.9
Classifier: Programming Language :: Python :: 3.10
Classifier: Programming Language :: Python :: 3.11
Classifier: Programming Language :: Python :: 3.12
Classifier: Programming Language :: Python :: 3.13
Classifier: Topic :: Software Development :: Libraries
Classifier: Topic :: Software Development :: Libraries :: Python Modules
License-File: LICENSE
Requires-Dist: dogpile.cache<1.5
Requires-Dist: importlib-metadata; python_version < "3.8"
Requires-Dist: python-dateutil<2.10
Requires-Dist: requests<3,>=2.27
Requires-Dist: six<2
Provides-Extra: develop
Requires-Dist: ruff<0.13; python_version >= "3.7" and extra == "develop"
Requires-Dist: twine<7; extra == "develop"
Requires-Dist: wheel<1; extra == "develop"
Provides-Extra: test
Requires-Dist: pytest<9; extra == "test"
Requires-Dist: pytest-cache<2; extra == "test"
Requires-Dist: pytest-cov<7.1; extra == "test"
Requires-Dist: python-dotenv<1.2; extra == "test"
Requires-Dist: responses<0.26; extra == "test"
Dynamic: author
Dynamic: author-email
Dynamic: classifier
Dynamic: description
Dynamic: description-content-type
Dynamic: download-url
Dynamic: home-page
Dynamic: keywords
Dynamic: license-file
Dynamic: maintainer
Dynamic: maintainer-email
Dynamic: provides-extra
Dynamic: requires-dist
Dynamic: summary
